idem_linux/conf.py
idem_linux/version.py
idem_linux/exec/linux/init.py
idem_linux/exec/linux/smbios.py
idem_linux/exec/linux/systemd_service.py
idem_linux/exec/linux/contracts/smbios.py
idem_linux/grains/linux/init.py
idem_linux/grains/linux/hw/bios.py
idem_linux/grains/linux/hw/gpu.py
idem_linux/grains/linux/hw/proc/cpu.py
idem_linux/grains/linux/hw/proc/mem.py
idem_linux/grains/linux/hw/storage/disks.py
idem_linux/grains/linux/hw/storage/iscsi.py
idem_linux/grains/linux/hw/storage/nvme.py
idem_linux/grains/linux/net/fibre_channel.py
idem_linux/grains/linux/net/gateway.py
idem_linux/grains/linux/net/interfaces.py
idem_linux/grains/linux/net/realm.py
idem_linux/grains/linux/os/arch.py
idem_linux/grains/linux/os/cpe.py
idem_linux/grains/linux/os/lsb_release.py
idem_linux/grains/linux/os/os.py
idem_linux/grains/linux/system/ps.py
idem_linux/grains/linux/system/selinux.py
idem_linux/states/init.py
idem_linux-7.2.dist-info/METADATA
idem_linux-7.2.dist-info/WHEEL
idem_linux-7.2.dist-info/top_level.txt
idem_linux-7.2.dist-info/RECORD
